blossy/__init__.py
blossy/blossy.py
blossy/calc.py
blossy/calct.py
blossy-8.5.dist-info/LICENSE
blossy-8.5.dist-info/METADATA
blossy-8.5.dist-info/WHEEL
blossy-8.5.dist-info/entry_points.txt
blossy-8.5.dist-info/top_level.txt
blossy-8.5.dist-info/RECORD
