Metadata-Version: 2.1
Name: blossy
Version: 8.5
Summary: A lil' bud that helps you with stuff (it's a utility CLI).
Author-email: Ryan Sakurai <ryansakurai03@gmail.com>
License: MIT License
Project-URL: repository, https://github.com/ryansakurai/blossy-cli
Classifier: Programming Language :: Python :: 3
Classifier: License :: OSI Approved :: MIT License
Classifier: Operating System :: OS Independent
License-File: LICENSE
Requires-Dist: click==8.1.7
Requires-Dist: colorama==0.4.6
Requires-Dist: markdown-it-py==3.0.0
Requires-Dist: mdurl==0.1.2
Requires-Dist: Pygments==2.17.2
Requires-Dist: rich==13.7.1
Requires-Dist: shellingham==1.5.4
Requires-Dist: sly==0.5
Requires-Dist: typer==0.9.0
Requires-Dist: typing_extensions==4.10.0
